dolphin_voice/__init__.py
dolphin_voice/speech_rec/__init__.py
dolphin_voice/speech_rec/_client.py
dolphin_voice/speech_rec/_log.py
dolphin_voice/speech_rec/_speech.py
dolphin_voice/speech_rec/_speech_asrfile.py
dolphin_voice/speech_rec/_speech_control.py
dolphin_voice/speech_rec/_speech_recognizer.py
dolphin_voice/speech_rec/_speech_transcriber.py
dolphin_voice/speech_rec/_token.py
dolphin_voice/speech_rec/_utils.py
dolphin_voice/speech_rec/callbacks.py
dolphin_voice/speech_rec/parameters.py
dolphin_voice/speech_syn/__init__.py
dolphin_voice/speech_syn/_client.py
dolphin_voice/speech_syn/_log.py
dolphin_voice/speech_syn/_speech.py
dolphin_voice/speech_syn/_speech_control.py
dolphin_voice/speech_syn/_speech_synthesizer.py
dolphin_voice/speech_syn/_token.py
dolphin_voice/speech_syn/_utils.py
dolphin_voice/speech_syn/callbacks.py
dolphin_voice/speech_syn/parameters.py
dolphin_voice-1.0.1.dist-info/licenses/LICENSE
dolphin_voice-1.0.1.dist-info/METADATA
dolphin_voice-1.0.1.dist-info/WHEEL
dolphin_voice-1.0.1.dist-info/top_level.txt
dolphin_voice-1.0.1.dist-info/RECORD
