Metadata-Version: 2.4
Name: dolphin_voice
Version: 1.0.1
Summary: SDK for dolphin-voice
Author-email: dolphinvoice <development@dolphin-ai.jp>
License: Apache License 2.0
Classifier: Development Status :: 3 - Alpha
Classifier: Intended Audience :: Developers
Classifier: License :: OSI Approved :: Apache Software License
Classifier: Programming Language :: Python :: 3
Classifier: Programming Language :: Python :: 3.6
Classifier: Programming Language :: Python :: 3.7
Classifier: Programming Language :: Python :: 3.8
Classifier: Programming Language :: Python :: 3.9
Classifier: Programming Language :: Python :: 3.10
Classifier: Programming Language :: Python :: 3.11
Requires-Python: >=3.6
License-File: LICENSE
Requires-Dist: websocket-client==1.4.0
Requires-Dist: requests
Requires-Dist: six
Requires-Dist: cryptography
Dynamic: license-file
